kafkaBridgeClient/__init__.py
kafkaBridgeClient/core.py
kafkaBridgeClient-0.1.5.dist-info/METADATA
kafkaBridgeClient-0.1.5.dist-info/RECORD
kafkaBridgeClient-0.1.5.dist-info/WHEEL
kafkaBridgeClient-0.1.5.dist-info/top_level.txt
