Metadata-Version: 2.1
Name: kafkaBridgeClient
Version: 0.1.5
Summary: A package for using kafka-bridge to talk to kafka inside docker
Home-page: https://gitlab.com/benkibejs/kafka-bridge/audentes
Author: Benjamin Lindberg
Author-email: benjamin.lindberg@gmail.com
License: UNKNOWN
Platform: UNKNOWN
Classifier: Programming Language :: Python :: 3
Classifier: License :: OSI Approved :: MIT License
Classifier: Operating System :: OS Independent
Requires-Dist: requests
